nlogo_utils/__init__.py
nlogo_utils/combine.py
nlogo_utils/common.py
nlogo_utils/extract.py
nlogo_utils/replace.py
nlogo_utils/shared.py
nlogo_utils/split.py
nlogo_utils-0.3.2.dist-info/LICENSE.txt
nlogo_utils-0.3.2.dist-info/METADATA
nlogo_utils-0.3.2.dist-info/WHEEL
nlogo_utils-0.3.2.dist-info/entry_points.txt
nlogo_utils-0.3.2.dist-info/top_level.txt
nlogo_utils-0.3.2.dist-info/RECORD
