Metadata-Version: 2.1
Name: nlogo-utils
Version: 0.3.2
Summary: Utilities to manipulate and create native NetLogo (.nlogo) files
Home-page: https://gitlab.com/breisfeld/nlogo_utils.git
Author: Brad Reisfeld
Author-email: brad.reisfeld@gmail.com
License: MIT
Platform: UNKNOWN
Classifier: Development Status :: 3 - Alpha
Classifier: Intended Audience :: Developers
Classifier: License :: OSI Approved :: MIT License
Classifier: Operating System :: OS Independent
Classifier: Programming Language :: Python
Classifier: Programming Language :: Python :: 3.6
Classifier: Programming Language :: Python :: 3.7
Classifier: Programming Language :: Python :: 3.8
Classifier: Programming Language :: Python :: 3.9
Classifier: Topic :: Software Development
Classifier: Topic :: Utilities
Requires-Python: >=3.6
